[
    {
     "name": "Genesis",
     "chapterCount": 50,
     "verseCounts": [
      31,
      25,
      24,
      26,
      32,
      22,
      24,
      22,
      29,
      32,
      32,
      20,
      18,
      24,
      21,
      16,
      27,
      33,
      38,
      18,
      34,
      24,
      20,
      67,
      34,
      35,
      46,
      22,
      35,
      43,
      55,
      32,
      20,
      31,
      29,
      43,
      36,
      30,
      23,
      23,
      57,
      38,
      34,
      34,
      28,
      34,
      31,
      22,
      33,
      26
     ],
     "abr": "Gen."
    },
    {
     "name": "Exodus",
     "chapterCount": 40,
     "verseCounts": [
      22,
      25,
      22,
      31,
      23,
      30,
      25,
      32,
      35,
      29,
      10,
      51,
      22,
      31,
      27,
      36,
      16,
      27,
      25,
      26,
      36,
      31,
      33,
      18,
      40,
      37,
      21,
      43,
      46,
      38,
      18,
      35,
      23,
      35,
      35,
      38,
      29,
      31,
      43,
      38
     ],
     "abr": "Ex."
    },
    {
     "name": "Leviticus",
     "chapterCount": 27,
     "verseCounts": [
      17,
      16,
      17,
      35,
      19,
      30,
      38,
      36,
      24,
      20,
      47,
      8,
      59,
      57,
      33,
      34,
      16,
      30,
      37,
      27,
      24,
      33,
      44,
      23,
      55,
      46,
      34
     ],
     "abr": "Lev."
    },
    {
     "name": "Numbers",
     "chapterCount": 36,
     "verseCounts": [
      54,
      34,
      51,
      49,
      31,
      27,
      89,
      26,
      23,
      36,
      35,
      16,
      33,
      45,
      41,
      50,
      13,
      32,
      22,
      29,
      35,
      41,
      30,
      25,
      18,
      65,
      23,
      31,
      40,
      16,
      54,
      42,
      56,
      29,
      34,
      13
     ],
     "abr": "Num."
    },
    {
     "name": "Deuteronomy",
     "chapterCount": 34,
     "verseCounts": [
      46,
      37,
      29,
      49,
      33,
      25,
      26,
      20,
      29,
      22,
      32,
      32,
      18,
      29,
      23,
      22,
      20,
      22,
      21,
      20,
      23,
      30,
      25,
      22,
      19,
      19,
      26,
      68,
      29,
      20,
      30,
      52,
      29,
      12
     ],
     "abr": "Deut."
    },
    {
     "name": "Joshua",
     "chapterCount": 24,
     "verseCounts": [
      18,
      24,
      17,
      24,
      15,
      27,
      26,
      35,
      27,
      43,
      23,
      24,
      33,
      15,
      63,
      10,
      18,
      28,
      51,
      9,
      45,
      34,
      16,
      33
     ],
     "abr": "Josh."
    },
    {
     "name": "Judges",
     "chapterCount": 21,
     "verseCounts": [
      36,
      23,
      31,
      24,
      31,
      40,
      25,
      35,
      57,
      18,
      40,
      15,
      25,
      20,
      20,
      31,
      13,
      31,
      30,
      48,
      25
     ],
     "abr": "Judg."
    },
    {
     "name": "Ruth",
     "chapterCount": 4,
     "verseCounts": [
      22,
      23,
      18,
      22
     ],
     "abr": "Ruth"
    },
    {
     "name": "1 Samuel",
     "chapterCount": 31,
     "verseCounts": [
      28,
      36,
      21,
      22,
      12,
      21,
      17,
      22,
      27,
      27,
      15,
      25,
      23,
      52,
      35,
      23,
      58,
      30,
      24,
      42,
      15,
      23,
      29,
      22,
      44,
      25,
      12,
      25,
      11,
      31,
      13
     ],
     "abr": "1 Sam."
    },
    {
     "name": "2 Samuel",
     "chapterCount": 24,
     "verseCounts": [
      27,
      32,
      39,
      12,
      25,
      23,
      29,
      18,
      13,
      19,
      27,
      31,
      39,
      33,
      37,
      23,
      29,
      33,
      43,
      26,
      22,
      51,
      39,
      25
     ],
     "abr": "2 Sam."
    },
    {
     "name": "1 Kings",
     "chapterCount": 22,
     "verseCounts": [
      53,
      46,
      28,
      34,
      18,
      38,
      51,
      66,
      28,
      29,
      43,
      33,
      34,
      31,
      34,
      34,
      24,
      46,
      21,
      43,
      29,
      53
     ],
     "abr": "1 Kings"
    },
    {
     "name": "2 Kings",
     "chapterCount": 25,
     "verseCounts": [
      18,
      25,
      27,
      44,
      27,
      33,
      20,
      29,
      37,
      36,
      21,
      21,
      25,
      29,
      38,
      20,
      41,
      37,
      37,
      21,
      26,
      20,
      37,
      20,
      30
     ],
     "abr": "2 Kings"
    },
    {
     "name": "1 Chronicles",
     "chapterCount": 29,
     "verseCounts": [
      54,
      55,
      24,
      43,
      26,
      81,
      40,
      40,
      44,
      14,
      47,
      40,
      14,
      17,
      29,
      43,
      27,
      17,
      19,
      8,
      30,
      19,
      32,
      31,
      31,
      32,
      34,
      21,
      30
     ],
     "abr": "1 Chron."
    },
    {
     "name": "2 Chronicles",
     "chapterCount": 36,
     "verseCounts": [
      17,
      18,
      17,
      22,
      14,
      42,
      22,
      18,
      31,
      19,
      23,
      16,
      22,
      15,
      19,
      14,
      19,
      34,
      11,
      37,
      20,
      12,
      21,
      27,
      28,
      23,
      9,
      27,
      36,
      27,
      21,
      33,
      25,
      33,
      27,
      23
     ],
     "abr": "2 Chron."
    },
    {
     "name": "Ezra",
     "chapterCount": 10,
     "verseCounts": [
      11,
      70,
      13,
      24,
      17,
      22,
      28,
      36,
      15,
      44
     ],
     "abr": "Ezra"
    },
    {
     "name": "Nehemiah",
     "chapterCount": 13,
     "verseCounts": [
      11,
      20,
      32,
      23,
      19,
      19,
      73,
      18,
      38,
      39,
      36,
      47,
      31
     ],
     "abr": "Neh."
    },
    {
     "name": "Esther",
     "chapterCount": 10,
     "verseCounts": [
      22,
      23,
      15,
      17,
      14,
      14,
      10,
      17,
      32,
      3
     ],
     "abr": "Est."
    },
    {
     "name": "Job",
     "chapterCount": 42,
     "verseCounts": [
      22,
      13,
      26,
      21,
      27,
      30,
      21,
      22,
      35,
      22,
      20,
      25,
      28,
      22,
      35,
      22,
      16,
      21,
      29,
      29,
      34,
      30,
      17,
      25,
      6,
      14,
      23,
      28,
      25,
      31,
      40,
      22,
      33,
      37,
      16,
      33,
      24,
      41,
      30,
      24,
      34,
      17
     ],
     "abr": "Job"
    },
    {
     "name": "Psalms",
     "chapterCount": 150,
     "verseCounts": [
      6,
      12,
      8,
      8,
      12,
      10,
      17,
      9,
      20,
      18,
      7,
      8,
      6,
      7,
      5,
      11,
      15,
      50,
      14,
      9,
      13,
      31,
      6,
      10,
      22,
      12,
      14,
      9,
      11,
      12,
      24,
      11,
      22,
      22,
      28,
      12,
      40,
      22,
      13,
      17,
      13,
      11,
      5,
      26,
      17,
      11,
      9,
      14,
      20,
      23,
      19,
      9,
      6,
      7,
      23,
      13,
      11,
      11,
      17,
      12,
      8,
      12,
      11,
      10,
      13,
      20,
      7,
      35,
      36,
      5,
      24,
      20,
      28,
      23,
      10,
      12,
      20,
      72,
      13,
      19,
      16,
      8,
      18,
      12,
      13,
      17,
      7,
      18,
      52,
      17,
      16,
      15,
      5,
      23,
      11,
      13,
      12,
      9,
      9,
      5,
      8,
      28,
      22,
      35,
      45,
      48,
      43,
      13,
      31,
      7,
      10,
      10,
      9,
      8,
      18,
      19,
      2,
      29,
      176,
      7,
      8,
      9,
      4,
      8,
      5,
      6,
      5,
      6,
      8,
      8,
      3,
      18,
      3,
      3,
      21,
      26,
      9,
      8,
      24,
      13,
      10,
      7,
      12,
      15,
      21,
      10,
      20,
      14,
      9,
      6
     ],
     "abr": "Ps."
    },
    {
     "name": "Proverbs",
     "chapterCount": 31,
     "verseCounts": [
      33,
      22,
      35,
      27,
      23,
      35,
      27,
      36,
      18,
      32,
      31,
      28,
      25,
      35,
      33,
      33,
      28,
      24,
      29,
      30,
      31,
      29,
      35,
      34,
      28,
      28,
      27,
      28,
      27,
      33,
      31
     ],
     "abr": "Prov."
    },
    {
     "name": "Ecclesiastes",
     "chapterCount": 12,
     "verseCounts": [
      18,
      26,
      22,
      16,
      20,
      12,
      29,
      17,
      18,
      20,
      10,
      14
     ],
     "abr": "Eccles."
    },
    {
     "name": "Song of Solomon",
     "chapterCount": 8,
     "verseCounts": [
      17,
      17,
      11,
      16,
      16,
      13,
      13,
      14
     ],
     "abr": "Song"
    },
    {
     "name": "Isaiah",
     "chapterCount": 66,
     "verseCounts": [
      31,
      22,
      26,
      6,
      30,
      13,
      25,
      22,
      21,
      34,
      16,
      6,
      22,
      32,
      9,
      14,
      14,
      7,
      25,
      6,
      17,
      25,
      18,
      23,
      12,
      21,
      13,
      29,
      24,
      33,
      9,
      20,
      24,
      17,
      10,
      22,
      38,
      22,
      8,
      31,
      29,
      25,
      28,
      28,
      25,
      13,
      15,
      22,
      26,
      11,
      23,
      15,
      12,
      17,
      13,
      12,
      21,
      14,
      21,
      22,
      11,
      12,
      19,
      12,
      25,
      24
     ],
     "abr": "Isa."
    },
    {
     "name": "Jeremiah",
     "chapterCount": 52,
     "verseCounts": [
      19,
      37,
      25,
      31,
      31,
      30,
      34,
      22,
      26,
      25,
      23,
      17,
      27,
      22,
      21,
      21,
      27,
      23,
      15,
      18,
      14,
      30,
      40,
      10,
      38,
      24,
      22,
      17,
      32,
      24,
      40,
      44,
      26,
      22,
      19,
      32,
      21,
      28,
      18,
      16,
      18,
      22,
      13,
      30,
      5,
      28,
      7,
      47,
      39,
      46,
      64,
      34
     ],
     "abr": "Jer."
    },
    {
     "name": "Lamentations",
     "chapterCount": 5,
     "verseCounts": [
      22,
      22,
      66,
      22,
      22
     ],
     "abr": "Lam."
    },
    {
     "name": "Ezekiel",
     "chapterCount": 48,
     "verseCounts": [
      28,
      10,
      27,
      17,
      17,
      14,
      27,
      18,
      11,
      22,
      25,
      28,
      23,
      23,
      8,
      63,
      24,
      32,
      14,
      49,
      32,
      31,
      49,
      27,
      17,
      21,
      36,
      26,
      21,
      26,
      18,
      32,
      33,
      31,
      15,
      38,
      28,
      23,
      29,
      49,
      26,
      20,
      27,
      31,
      25,
      24,
      23,
      35
     ],
     "abr": "Ezek."
    },
    {
     "name": "Daniel",
     "chapterCount": 12,
     "verseCounts": [
      21,
      49,
      30,
      37,
      31,
      28,
      28,
      27,
      27,
      21,
      45,
      13
     ],
     "abr": "Dan."
    },
    {
     "name": "Hosea",
     "chapterCount": 14,
     "verseCounts": [
      11,
      23,
      5,
      19,
      15,
      11,
      16,
      14,
      17,
      15,
      12,
      14,
      16,
      9
     ],
     "abr": "Hos."
    },
    {
     "name": "Joel",
     "chapterCount": 3,
     "verseCounts": [
      20,
      32,
      21
     ],
     "abr": "Joel"
    },
    {
     "name": "Amos",
     "chapterCount": 9,
     "verseCounts": [
      15,
      16,
      15,
      13,
      27,
      14,
      17,
      14,
      15
     ],
     "abr": "Amos"
    },
    {
     "name": "Obadiah",
     "chapterCount": 1,
     "verseCounts": [
      21
     ],
     "abr": "Obad."
    },
    {
     "name": "Jonah",
     "chapterCount": 4,
     "verseCounts": [
      17,
      10,
      10,
      11
     ],
     "abr": "Jonah"
    },
    {
     "name": "Micah",
     "chapterCount": 7,
     "verseCounts": [
      16,
      13,
      12,
      13,
      15,
      16,
      20
     ],
     "abr": "Mic."
    },
    {
     "name": "Nahum",
     "chapterCount": 3,
     "verseCounts": [
      15,
      13,
      19
     ],
     "abr": "Nah."
    },
    {
     "name": "Habakkuk",
     "chapterCount": 3,
     "verseCounts": [
      17,
      20,
      19
     ],
     "abr": "Hab."
    },
    {
     "name": "Zephaniah",
     "chapterCount": 3,
     "verseCounts": [
      18,
      15,
      20
     ],
     "abr": "Zeph."
    },
    {
     "name": "Haggai",
     "chapterCount": 2,
     "verseCounts": [
      15,
      23
     ],
     "abr": "Hag."
    },
    {
     "name": "Zechariah",
     "chapterCount": 14,
     "verseCounts": [
      21,
      13,
      10,
      14,
      11,
      15,
      14,
      23,
      17,
      12,
      17,
      14,
      9,
      21
     ],
     "abr": "Zech."
    },
    {
     "name": "Malachi",
     "chapterCount": 4,
     "verseCounts": [
      14,
      17,
      18,
      6
     ],
     "abr": "Mal."
    },
    {
     "name": "Matthew",
     "chapterCount": 28,
     "verseCounts": [
      25,
      23,
      17,
      25,
      48,
      34,
      29,
      34,
      38,
      42,
      30,
      50,
      58,
      36,
      39,
      28,
      27,
      35,
      30,
      34,
      46,
      46,
      39,
      51,
      46,
      75,
      66,
      20
     ],
     "abr": "Matt."
    },
    {
     "name": "Mark",
     "chapterCount": 16,
     "verseCounts": [
      45,
      28,
      35,
      41,
      43,
      56,
      37,
      38,
      50,
      52,
      33,
      44,
      37,
      72,
      47,
      20
     ],
     "abr": "Mark"
    },
    {
     "name": "Luke",
     "chapterCount": 24,
     "verseCounts": [
      80,
      52,
      38,
      44,
      39,
      49,
      50,
      56,
      62,
      42,
      54,
      59,
      35,
      35,
      32,
      31,
      37,
      43,
      48,
      47,
      38,
      71,
      56,
      53
     ],
     "abr": "Luke"
    },
    {
     "name": "John",
     "chapterCount": 21,
     "verseCounts": [
      51,
      25,
      36,
      54,
      47,
      71,
      53,
      59,
      41,
      42,
      57,
      50,
      38,
      31,
      27,
      33,
      26,
      40,
      42,
      31,
      25
     ],
     "abr": "John"
    },
    {
     "name": "Acts",
     "chapterCount": 28,
     "verseCounts": [
      26,
      47,
      26,
      37,
      42,
      15,
      60,
      40,
      43,
      48,
      30,
      25,
      52,
      28,
      41,
      40,
      34,
      28,
      41,
      38,
      40,
      30,
      35,
      27,
      27,
      32,
      44,
      31
     ],
     "abr": "Acts"
    },
    {
     "name": "Romans",
     "chapterCount": 16,
     "verseCounts": [
      32,
      29,
      31,
      25,
      21,
      23,
      25,
      39,
      33,
      21,
      36,
      21,
      14,
      26,
      33,
      25
     ],
     "abr": "Rom."
    },
    {
     "name": "1 Corinthians",
     "chapterCount": 16,
     "verseCounts": [
      31,
      16,
      23,
      21,
      13,
      20,
      40,
      13,
      27,
      33,
      34,
      31,
      13,
      40,
      58,
      24
     ],
     "abr": "1 Cor."
    },
    {
     "name": "2 Corinthians",
     "chapterCount": 13,
     "verseCounts": [
      24,
      17,
      18,
      18,
      21,
      18,
      16,
      24,
      15,
      18,
      33,
      21,
      14
     ],
     "abr": "2 Cor."
    },
    {
     "name": "Galatians",
     "chapterCount": 6,
     "verseCounts": [
      24,
      21,
      29,
      31,
      26,
      18
     ],
     "abr": "Gal."
    },
    {
     "name": "Ephesians",
     "chapterCount": 6,
     "verseCounts": [
      23,
      22,
      21,
      32,
      33,
      24
     ],
     "abr": "Eph."
    },
    {
     "name": "Philippians",
     "chapterCount": 4,
     "verseCounts": [
      30,
      30,
      21,
      23
     ],
     "abr": "Phil."
    },
    {
     "name": "Colossians",
     "chapterCount": 4,
     "verseCounts": [
      29,
      23,
      25,
      18
     ],
     "abr": "Col."
    },
    {
     "name": "1 Thessalonians",
     "chapterCount": 5,
     "verseCounts": [
      10,
      20,
      13,
      18,
      28
     ],
     "abr": "1 Thess."
    },
    {
     "name": "2 Thessalonians",
     "chapterCount": 3,
     "verseCounts": [
      12,
      17,
      18
     ],
     "abr": "2 Thess."
    },
    {
     "name": "1 Timothy",
     "chapterCount": 6,
     "verseCounts": [
      20,
      15,
      16,
      16,
      25,
      21
     ],
     "abr": "1 Tim."
    },
    {
     "name": "2 Timothy",
     "chapterCount": 4,
     "verseCounts": [
      18,
      26,
      17,
      22
     ],
     "abr": "2 Tim."
    },
    {
     "name": "Titus",
     "chapterCount": 3,
     "verseCounts": [
      16,
      15,
      15
     ],
     "abr": "Titus"
    },
    {
     "name": "Philemon",
     "chapterCount": 1,
     "verseCounts": [
      25
     ],
     "abr": "Philem."
    },
    {
     "name": "Hebrews",
     "chapterCount": 13,
     "verseCounts": [
      14,
      18,
      19,
      16,
      14,
      20,
      28,
      13,
      28,
      39,
      40,
      29,
      25
     ],
     "abr": "Heb."
    },
    {
     "name": "James",
     "chapterCount": 5,
     "verseCounts": [
      27,
      26,
      18,
      17,
      20
     ],
     "abr": "James"
    },
    {
     "name": "1 Peter",
     "chapterCount": 5,
     "verseCounts": [
      25,
      25,
      22,
      19,
      14
     ],
     "abr": "1 Pet."
    },
    {
     "name": "2 Peter",
     "chapterCount": 3,
     "verseCounts": [
      21,
      22,
      18
     ],
     "abr": "2 Pet."
    },
    {
     "name": "1 John",
     "chapterCount": 5,
     "verseCounts": [
      10,
      29,
      24,
      21,
      21
     ],
     "abr": "1 John"
    },
    {
     "name": "2 John",
     "chapterCount": 1,
     "verseCounts": [
      13
     ],
     "abr": "2 John"
    },
    {
     "name": "3 John",
     "chapterCount": 1,
     "verseCounts": [
      14
     ],
     "abr": "3 John"
    },
    {
     "name": "Jude",
     "chapterCount": 1,
     "verseCounts": [
      25
     ],
     "abr": "Jude"
    },
    {
     "name": "Revelation",
     "chapterCount": 22,
     "verseCounts": [
      20,
      29,
      22,
      11,
      14,
      17,
      17,
      13,
      21,
      11,
      19,
      17,
      18,
      20,
      8,
      21,
      18,
      24,
      21,
      15,
      27,
      21
     ],
     "abr": "Rev."
    }
   ]